Metadata-Version: 2.1
Name: muriki
Version: 0.2.5
Summary: An utility to import data and persist data
Home-page: https://github.com/1ber/muriki
Author: Humberto Ramos Costa
Author-email: 1bertorc@gmail.com
License:                                  Apache License
